SocksDriver/__init__.py
SocksDriver/client.py
SocksDriver/errors.py
SocksDriver-1.5.dist-info/LICENSE
SocksDriver-1.5.dist-info/METADATA
SocksDriver-1.5.dist-info/WHEEL
SocksDriver-1.5.dist-info/top_level.txt
SocksDriver-1.5.dist-info/RECORD
