Metadata-Version: 2.1
Name: SocksDriver
Version: 1.5
Summary: Driver for proprietary ChristmasSocks server
Author: David Weber
Classifier: Programming Language :: Python :: 3
Classifier: License :: OSI Approved :: MIT License
Classifier: Operating System :: OS Independent
Requires-Python: >=3.9
License-File: LICENSE
